{"type":"FeatureCollection","features":[{"type":"Feature","properties":{"best_match_score":0.39676382796076426,"__id_left":"83_left","__id_right":"76_right","text":"JOY PHARMACY INC","ADDRESS_LINE1_left":"1302 E 6th Ave","CITY":"Denver","STATE":"CO","ADDRESS_LINE1_right":"1302 E 6th Ave","status":"OK","duration_text":"6 mins","duration_value":339},"geometry":{"type":"Point","coordinates":[-104.971521,39.725464]}},{"type":"Feature","properties":{"best_match_score":0.41683249433836295,"__id_left":"93_left","__id_right":"85_right","text":"CAPITOL HILL LIQUORS","ADDRESS_LINE1_left":"1032 E 9th Ave","CITY":"Denver","STATE":"CO","ADDRESS_LINE1_right":"1032 E 9th Ave","status":"OK","duration_text":"6 mins","duration_value":336},"geometry":{"type":"Point","coordinates":[-104.974297,39.730302]}},{"type":"Feature","properties":{"best_match_score":0.40092845251437426,"__id_left":"103_left","__id_right":"94_right","text":"HUGO'S COLORADO BEER AND SPIRITS","ADDRESS_LINE1_left":"1205 E 13th Ave","CITY":"Denver","STATE":"CO","ADDRESS_LINE1_right":"1205 E 13th Ave","status":"OK","duration_text":"15 mins","duration_value":872},"geometry":{"type":"Point","coordinates":[-104.972735,39.736988]}},{"type":"Feature","properties":{"best_match_score":0.4419388309604689,"__id_left":"221_left","__id_right":"205_right","text":null,"ADDRESS_LINE1_left":"788 N Marion St","CITY":"Denver","STATE":"CO","ADDRESS_LINE1_right":"788 N Marion St","status":"OK","duration_text":"1 min","duration_value":33},"geometry":{"type":"Point","coordinates":[-104.971507,39.728886]}}]}